peewee_enum_field/__init__.py
peewee_enum_field-0.2.0.dist-info/LICENSE
peewee_enum_field-0.2.0.dist-info/METADATA
peewee_enum_field-0.2.0.dist-info/WHEEL
peewee_enum_field-0.2.0.dist-info/RECORD
