Metadata-Version: 2.1
Name: peewee-enum-field
Version: 0.2.0
Summary: A custom EnumField for Peewee ORM to handle Python Enum types.
License: MIT
Author: Sebastian Kucharzyk
Author-email: kucharzyk.sebastian@gmail.com
Requires-Python: >=3.9,<4.0
Classifier: License :: OSI Approved :: MIT License
Classifier: Programming Language :: Python :: 3
Classifier: Programming Language :: Python :: 3.9
Classifier: Programming Language :: Python :: 3.10
Classifier: Programming Language :: Python :: 3.11
Classifier: Programming Language :: Python :: 3.12
Requires-Dist: peewee (>=3.15.0,<4.0.0)
